lxsSimpleTools/__init__.py
lxsSimpleTools/binaryTools.py
lxsSimpleTools/ipTools.py
lxsSimpleTools/strTools.py
lxsSimpleTools/timeTools.py
lxs_SimpleTools-2.0.0.dist-info/METADATA
lxs_SimpleTools-2.0.0.dist-info/WHEEL
lxs_SimpleTools-2.0.0.dist-info/top_level.txt
lxs_SimpleTools-2.0.0.dist-info/RECORD
