Metadata-Version: 2.1
Name: lxs-SimpleTools
Version: 2.0.0
Summary: 处理字符串和时间简单工具函数
Author: liuxiansong
Author-email: 326427540@qq.com
Classifier: Development Status :: 5 - Production/Stable
Classifier: Intended Audience :: Developers
Classifier: License :: OSI Approved :: MIT License
Classifier: Programming Language :: Python :: 3
Classifier: Programming Language :: Python :: 3.6
Classifier: Programming Language :: Python :: 3.7
Classifier: Programming Language :: Python :: 3.8
